.gitignore
.pre-commit-config.yaml
.readthedocs.yaml
CHANGELOG.rst
LICENSE
README.md
config.yaml
pyproject.toml
.github/dependabot.yml
.github/ISSUE_TEMPLATE/bug_report.md
.github/ISSUE_TEMPLATE/feature_request.md
.github/workflows/ci-punchpipe-dev.yaml
.github/workflows/ci.yaml
.github/workflows/ci_fixed.yaml
.github/workflows/python-publish.yaml
docs/Makefile
docs/make.bat
docs/source/conf.py
docs/source/index.rst
docs/source/_static/favicon.ico
docs/source/_static/logo.png
docs/source/control/configuration.rst
docs/source/control/index.rst
docs/source/control/states.rst
docs/source/levels/index.rst
punchpipe/__init__.py
punchpipe/cli.py
punchpipe/cluster.py
punchpipe/error.py
punchpipe.egg-info/PKG-INFO
punchpipe.egg-info/SOURCES.txt
punchpipe.egg-info/dependency_links.txt
punchpipe.egg-info/entry_points.txt
punchpipe.egg-info/requires.txt
punchpipe.egg-info/top_level.txt
punchpipe/control/__init__.py
punchpipe/control/cache_nanny.py
punchpipe/control/cleaner.py
punchpipe/control/db.py
punchpipe/control/health.py
punchpipe/control/launcher.py
punchpipe/control/processor.py
punchpipe/control/scheduler.py
punchpipe/control/util.py
punchpipe/control/cache_layer/__init__.py
punchpipe/control/cache_layer/loader_base_class.py
punchpipe/control/cache_layer/manager.py
punchpipe/control/cache_layer/nfi_l1.py
punchpipe/control/cache_layer/psf.py
punchpipe/control/cache_layer/quartic_coefficients.py
punchpipe/control/cache_layer/vignetting_function.py
punchpipe/control/tests/__init__.py
punchpipe/control/tests/conftest.py
punchpipe/control/tests/punchpipe_config.yaml
punchpipe/control/tests/test_cleaner.py
punchpipe/control/tests/test_launcher.py
punchpipe/control/tests/test_processor.py
punchpipe/control/tests/test_scheduler.py
punchpipe/control/tests/test_util.py
punchpipe/flows/__init__.py
punchpipe/flows/fcorona.py
punchpipe/flows/level0.py
punchpipe/flows/level1.py
punchpipe/flows/level2.py
punchpipe/flows/level3.py
punchpipe/flows/levelh.py
punchpipe/flows/levelq.py
punchpipe/flows/simulate.py
punchpipe/flows/starfield.py
punchpipe/flows/stray_light.py
punchpipe/flows/util.py
punchpipe/flows/velocity.py
punchpipe/flows/visualize.py
