Metadata-Version: 2.4
Name: punchpipe
Version: 0.0.13
Summary: PUNCH mission's data reduction pipeline
Author-email: "J. Marcus Hughes" <hughes.jmb@gmail.com>
Maintainer-email: "J. Marcus Hughes" <hughes.jmb@gmail.com>
License: Copyright (c) 2024 PUNCH Science Operations Center
Project-URL: Repository, https://github.com/punch-mission/punchpipe.git
Project-URL: Bug Tracker, https://github.com/punch-mission/punchpipe/issues
Keywords: TODO
Classifier: Development Status :: 4 - Beta
Classifier: Programming Language :: Python
Requires-Python: >=3.11
License-File: LICENSE
Requires-Dist: ccsdspy
Requires-Dist: punchbowl
Requires-Dist: simpunch
Requires-Dist: prefect[sqlalchemy]
Requires-Dist: pymysql
Requires-Dist: pandas
Requires-Dist: xlrd
Requires-Dist: pydantic
Requires-Dist: sqlalchemy
Requires-Dist: dash
Requires-Dist: dash-bootstrap-components
Requires-Dist: coolname
Requires-Dist: numpy
Requires-Dist: plotly
Requires-Dist: pyyaml
Requires-Dist: click
Requires-Dist: pylibjpeg[libjpeg]
Requires-Dist: psutil
Requires-Dist: gunicorn
Requires-Dist: numpy-quaternion
Requires-Dist: hypothesis==6.131.18
Requires-Dist: coverage==7.8.0
Requires-Dist: pytest-cov==6.1.1
Requires-Dist: dash-player==1.1.0
Requires-Dist: astrometry==4.3.0
Provides-Extra: test
Requires-Dist: pre-commit; extra == "test"
Requires-Dist: hypothesis; extra == "test"
Requires-Dist: pytest; extra == "test"
Requires-Dist: coverage; extra == "test"
Requires-Dist: pytest-cov; extra == "test"
Requires-Dist: pytest-mock-resources[mysql]; extra == "test"
Requires-Dist: freezegun; extra == "test"
Requires-Dist: ruff; extra == "test"
Provides-Extra: docs
Requires-Dist: packaging; extra == "docs"
Requires-Dist: sphinx; extra == "docs"
Requires-Dist: pydata-sphinx-theme; extra == "docs"
Requires-Dist: sphinx-autoapi; extra == "docs"
Requires-Dist: sphinx-favicon; extra == "docs"
Requires-Dist: sphinxcontrib-mermaid; extra == "docs"
Requires-Dist: sphinx-automodapi; extra == "docs"
Provides-Extra: dev
Requires-Dist: punchpipe[docs,test]; extra == "dev"
Requires-Dist: pre-commit; extra == "dev"
Dynamic: license-file
